bobcatpy.py
bobcatpy-1.0.0.dist-info/LICENSE
bobcatpy-1.0.0.dist-info/METADATA
bobcatpy-1.0.0.dist-info/WHEEL
bobcatpy-1.0.0.dist-info/top_level.txt
bobcatpy-1.0.0.dist-info/RECORD
