Metadata-Version: 2.1
Name: bobcatpy
Version: 1.0.0
Summary: Control and monitor your Bobcat miner
Home-page: https://github.com/ardevd/bobcatpy
Author: ardevd
Author-email: 5gk633atf@relay.firefox.com
License: UNKNOWN
Platform: UNKNOWN
Classifier: Programming Language :: Python :: 3
Classifier: License :: OSI Approved :: MIT License
Classifier: Operating System :: OS Independent
Classifier: Intended Audience :: Developers
Classifier: Development Status :: 5 - Production/Stable
License-File: LICENSE
